odoo/addons/partner_risk_insurance/README.rst
odoo/addons/partner_risk_insurance/__init__.py
odoo/addons/partner_risk_insurance/__manifest__.py
odoo/addons/partner_risk_insurance/hooks.py
odoo/addons/partner_risk_insurance/i18n/ca.po
odoo/addons/partner_risk_insurance/i18n/es.po
odoo/addons/partner_risk_insurance/i18n/it.po
odoo/addons/partner_risk_insurance/i18n/partner_risk_insurance.pot
odoo/addons/partner_risk_insurance/i18n/pt.po
odoo/addons/partner_risk_insurance/i18n/pt_BR.po
odoo/addons/partner_risk_insurance/i18n/sl.po
odoo/addons/partner_risk_insurance/models/__init__.py
odoo/addons/partner_risk_insurance/models/account_move.py
odoo/addons/partner_risk_insurance/models/credit_policy_company.py
odoo/addons/partner_risk_insurance/models/credit_policy_state.py
odoo/addons/partner_risk_insurance/models/res_partner.py
odoo/addons/partner_risk_insurance/readme/CONTRIBUTORS.md
odoo/addons/partner_risk_insurance/readme/DESCRIPTION.md
odoo/addons/partner_risk_insurance/readme/USAGE.md
odoo/addons/partner_risk_insurance/security/ir.model.access.csv
odoo/addons/partner_risk_insurance/static/description/icon.png
odoo/addons/partner_risk_insurance/static/description/index.html
odoo/addons/partner_risk_insurance/templates/invoice_risk_insurance_template.xml
odoo/addons/partner_risk_insurance/tests/__init__.py
odoo/addons/partner_risk_insurance/tests/test_invoice_credit_policy.py
odoo/addons/partner_risk_insurance/tests/test_partner_risk_insurance.py
odoo/addons/partner_risk_insurance/views/account_move_view.xml
odoo/addons/partner_risk_insurance/views/credit_policy_company_view.xml
odoo/addons/partner_risk_insurance/views/res_partner_view.xml
odoo/addons/partner_risk_insurance/wizard/__init__.py
odoo/addons/partner_risk_insurance/wizard/invoice_risk_insurance_wizard.py
odoo/addons/partner_risk_insurance/wizard/invoice_risk_insurance_wizard.xml
odoo_addon_partner_risk_insurance-18.0.1.0.3.dist-info/METADATA
odoo_addon_partner_risk_insurance-18.0.1.0.3.dist-info/WHEEL
odoo_addon_partner_risk_insurance-18.0.1.0.3.dist-info/top_level.txt
odoo_addon_partner_risk_insurance-18.0.1.0.3.dist-info/RECORD
