Metadata-Version: 2.1
Name: odoo-addon-partner_risk_insurance
Version: 18.0.1.0.3
Requires-Python: >=3.10
Requires-Dist: odoo==18.0.*
Summary: Risk insurance partner information
Home-page: https://github.com/OCA/credit-control
License: AGPL-3
Author: =?utf-8?q?AvanzOSC=2CTecnativa=2CFactor_Libre_S=2EL=2CNaN=C2=B7tic=2CModuon=2COdoo_Community_Association_=28OCA=29?=
Author-email: support@odoo-community.org
Classifier: Programming Language :: Python
Classifier: Framework :: Odoo
Classifier: Framework :: Odoo :: 18.0
Classifier: License :: OSI Approved :: GNU Affero General Public License v3
Classifier: Development Status :: 5 - Production/Stable
